exchange_rates/__init__.py
exchange_rates/app.py
exchange_rates/httpClient.py
exchange_rates/main.py
exchange_rates_selim-0.2.dist-info/LICENSE
exchange_rates_selim-0.2.dist-info/METADATA
exchange_rates_selim-0.2.dist-info/WHEEL
exchange_rates_selim-0.2.dist-info/entry_points.txt
exchange_rates_selim-0.2.dist-info/top_level.txt
exchange_rates_selim-0.2.dist-info/RECORD
